django_debug_false_checker/__init__.py
django_debug_false_checker/__main__.py
django_debug_false_checker-0.0.4.dist-info/LICENSE
django_debug_false_checker-0.0.4.dist-info/METADATA
django_debug_false_checker-0.0.4.dist-info/WHEEL
django_debug_false_checker-0.0.4.dist-info/entry_points.txt
django_debug_false_checker-0.0.4.dist-info/top_level.txt
django_debug_false_checker-0.0.4.dist-info/RECORD
