Metadata-Version: 2.1
Name: django-debug-false-checker
Version: 0.0.4
Summary: Check that you're not changing the django DEBUG's setting by mistake.
Home-page: https://github.com/Pierre-Sassoulas/django-debug-false-checker/
Author: Pierre Sassoulas
Author-email: pierre.sassoulas@gmail.com
Classifier: Operating System :: OS Independent
Classifier: Intended Audience :: Developers
Classifier: License :: OSI Approved :: MIT License
Classifier: Programming Language :: Python :: 3.7
Classifier: Programming Language :: Python :: 3.8
Classifier: Programming Language :: Python :: 3.9
Classifier: Programming Language :: Python :: 3.10
Classifier: Programming Language :: Python :: 3.11
Classifier: Development Status :: 5 - Production/Stable
License-File: LICENSE
Provides-Extra: test
Requires-Dist: pytest-cov ; extra == 'test'
Requires-Dist: pytest-vcr ; extra == 'test'
Requires-Dist: coverage ; extra == 'test'
Requires-Dist: python-coveralls ; extra == 'test'
Requires-Dist: coveralls ; extra == 'test'
Requires-Dist: pylint (~=2.15.10) ; extra == 'test'
Requires-Dist: pre-commit ; extra == 'test'
Requires-Dist: tbump ; extra == 'test'
